Metadata-Version: 2.1
Name: google-drive-manager
Version: 1.0.4
Summary: Un gestionnaire de Google Drive
Home-page: UNKNOWN
Author: Guillaume LECOSSOIS
Author-email: <guillaume.lecossois@diabeloop.fr>
License: UNKNOWN
Keywords: python,google,drive
Platform: UNKNOWN
Requires-Python: >=3.8
